{
    "similarity": 0.2967793047428131,
    "hash": 8680142242950134877,
    "punsafe": 0.021339714527130127,
    "pwatermark": 0.26522013545036316,
    "aesthetic": 7.822092533111572,
    "caption": "A Touch Of Class With Prada Wedding Gowns. Blue Wedding Dress Dream Meaning. Backless Wedding Dresses Online Australia. Second Hand Vintage Style Wedding Dresses. Pink Wedding Dress Photos. Wedding Dresses Column Style. Wedding Dresses Less Than $50. Disney Wedding Dresses Tiana. Winter Wedding Dresses Nz",
    "url": "https://tse4.mm.bing.net/th?id=OIP.k9tvo3nOSLZ6YQSWQJS3oAHaJ3&amp;w=131&amp;h=131",
    "key": "000014037",
    "status": "success",
    "error_message": null,
    "width": 384,
    "height": 511,
    "original_width": 474,
    "original_height": 631,
    "exif": "{\"Image ExifOffset\": \"26\", \"EXIF Tag 0x4000\": \"35\", \"EXIF Tag 0x4001\": \"0\"}",
    "sha256": "01c1352062030183a722f13ad6f0ccab3cbdedb77e924e7d46dd5b44a2740ede"
}