{
    "similarity": 0.316799134016037,
    "hash": 8314067903830358812,
    "punsafe": 1.765381398399768e-06,
    "pwatermark": 0.11100982874631882,
    "aesthetic": 7.189727306365967,
    "caption": "Fiat Marea Weekend 2000/2001",
    "url": "https://http2.mlstatic.com/D_NQ_NP_603984-MLB40821413117_022020-W.jpg",
    "key": "000014511",
    "status": "success",
    "error_message": null,
    "width": 512,
    "height": 384,
    "original_width": 568,
    "original_height": 426,
    "exif": "{}",
    "sha256": "c3a82c64e8b2b3977ea35f8920d06cefc9842b5da67456bb1a223b826f483551"
}