{
    "similarity": 0.3183652460575104,
    "hash": 3914573218093615054,
    "punsafe": 7.558465586043894e-05,
    "pwatermark": 0.06614850461483002,
    "aesthetic": 7.092500686645508,
    "caption": "Top 17 Mason Jar Cocktails",
    "url": "https://stevethebartender.com.au/wp-content/uploads/2013/09/mojito-mason-jar.jpg",
    "key": "000015086",
    "status": "success",
    "error_message": null,
    "width": 384,
    "height": 462,
    "original_width": 490,
    "original_height": 590,
    "exif": "{}",
    "sha256": "c22755c4e4bdbbe0434ac3fa417e40137a1dcc8a58d61c9ac9e5bb608f8ac99c"
}