{
    "similarity": 0.3732118010520935,
    "hash": 2092422130880886902,
    "punsafe": 9.601293641026132e-06,
    "pwatermark": 0.24793119728565216,
    "aesthetic": 7.303643703460693,
    "caption": "Alister the Parrot Needlepoint Kit Elizabeth Bradley Design Sand",
    "url": "https://cdn.shopify.com/s/files/1/0070/9486/1935/products/alister-the-parrot-needlepoint-kit-elizabeth-bradley-design-sand-681411_800x.jpg?v=1556050685",
    "key": "000013281",
    "status": "success",
    "error_message": null,
    "width": 384,
    "height": 384,
    "original_width": 500,
    "original_height": 500,
    "exif": "{\"Image HostComputer\": \"imagery4\"}",
    "sha256": "bdd5e2e5ee1733abd7d3042fc867b0411af935b97cf322325bd597b1b1e46f75"
}