{
    "similarity": 0.30484458804130554,
    "hash": 7374117928558430446,
    "punsafe": 0.0003624558448791504,
    "pwatermark": 0.3275500535964966,
    "aesthetic": 7.13097620010376,
    "caption": "Pixie Chicks: Happy Valentine's Day Photo Idea for Cards...{luv the tshirt idea too!}",
    "url": "https://i.pinimg.com/236x/ad/44/ce/ad44ce2d42840cade3e1e922b54c5ac7--valentines-day-pictures-ideas-for-valentines-day.jpg",
    "key": "000014190",
    "status": "success",
    "error_message": null,
    "width": 236,
    "height": 354,
    "original_width": 236,
    "original_height": 354,
    "exif": "{}",
    "sha256": "1557ed552d26a56d1a8d983a498e397035231d3899c4f94e5f8099660a88aad7"
}