{
    "similarity": 0.29813629388809204,
    "hash": 4238074984601810226,
    "punsafe": 0.4584733545780182,
    "pwatermark": 0.16072767972946167,
    "aesthetic": 7.175059795379639,
    "caption": "Madonna photographed by Steven Meisel",
    "url": "http://i.pinimg.com/236x/a1/ca/73/a1ca7386f971710e2394d7e9ce82af43.jpg",
    "key": "000014300",
    "status": "success",
    "error_message": null,
    "width": 236,
    "height": 321,
    "original_width": 236,
    "original_height": 321,
    "exif": "{}",
    "sha256": "25274aec577f441f0b67ff5737682a5214a6d470ae9a869fd006f179c3afb974"
}