{
    "similarity": 0.3330811560153961,
    "hash": 2505892943390973714,
    "punsafe": 0.001598358154296875,
    "pwatermark": 0.36080294847488403,
    "aesthetic": 7.242581367492676,
    "caption": "Pink hearts out of open envelope and blank greeting card",
    "url": "https://img.freepik.com/free-photo/pink-hearts-out-open-envelope-blank-greeting-card_78048-394.jpg?size=626&ext=jpg",
    "key": "000015012",
    "status": "success",
    "error_message": null,
    "width": 578,
    "height": 384,
    "original_width": 626,
    "original_height": 416,
    "exif": "{}",
    "sha256": "43960a86a60d4c4ac9ba3266eb2f7bcc4feffa47b52ffeb1c10ce72c5a1e21a7"
}