{
    "similarity": 0.3737793564796448,
    "hash": 4682478076748100628,
    "punsafe": 0.0003966391086578369,
    "pwatermark": 0.09936614334583282,
    "aesthetic": 7.795875072479248,
    "caption": "Fun beachy table decorations for a luau party - coconuts, grass skirts, leis  more #luau #beach #party",
    "url": "https://i.pinimg.com/originals/31/ee/d1/31eed16479b90190ce9d818f17abcb45.jpg",
    "key": "000013844",
    "status": "success",
    "error_message": null,
    "width": 576,
    "height": 384,
    "original_width": 600,
    "original_height": 400,
    "exif": "{}",
    "sha256": "40f9e1fa2afc22fd32b0f4d128b0931b5e9009d3c46b900c9224c4c47f40214d"
}