{
    "similarity": 0.3686959445476532,
    "hash": 1467140145556166797,
    "punsafe": 6.169525022414746e-06,
    "pwatermark": 0.06438851356506348,
    "aesthetic": 7.4259748458862305,
    "caption": "Painting - Chase Park Plaza In Winter, St.louis by Irek Szelag",
    "url": "https://render.fineartamerica.com/images/rendered/search/print/images/artworkimages/medium/1/chase-park-plaza-in-winter-stlouis-irek-szelag.jpg",
    "key": "000014175",
    "status": "success",
    "error_message": null,
    "width": 400,
    "height": 322,
    "original_width": 400,
    "original_height": 322,
    "exif": "{}",
    "sha256": "fa52db42fd5da8e315b56e6eea40674f218237f7d55a1899d8c3e3700a046eca"
}