{
    "similarity": 0.3375561237335205,
    "hash": -2481307245335864584,
    "punsafe": 0.0017256736755371094,
    "pwatermark": 0.13848397135734558,
    "aesthetic": 7.187582492828369,
    "caption": "WINDSOR, CAUSA - June 20, 2015: 25th Annual Sonoma County Hot Air Balloon Classic is a yearly event where you can experience balloons up close, watch them launch, and even take tethered rides.",
    "url": "https://us.123rf.com/450wm/melastmohican/melastmohican1506/melastmohican150600357/41359340-windsor-ca-usa-june-20-2015-25th-annual-sonoma-county-hot-air-balloon-classic-is-a-yearly-event-wher.jpg?ver=6",
    "key": "000014404",
    "status": "success",
    "error_message": null,
    "width": 450,
    "height": 338,
    "original_width": 450,
    "original_height": 338,
    "exif": "{}",
    "sha256": "43bfb1e3e09902458a2c8b71d80d318b05ba2bc8dc04df77e451a73d6f85e62c"
}