{
    "similarity": 0.3021075427532196,
    "hash": 1441698196748221457,
    "punsafe": 0.0009088218212127686,
    "pwatermark": 0.06636612117290497,
    "aesthetic": 7.215875625610352,
    "caption": "31 Funniest Memes and Pics Crazy Kooky and Comical ~ -woman covered n frosted pop tarts suit",
    "url": "https://i1.wp.com/teamjimmyjoe.com/wp-content/uploads/2019/03/funny-pop-tart-woman.jpg?resize=620%2C826&",
    "key": "000014387",
    "status": "success",
    "error_message": null,
    "width": 384,
    "height": 512,
    "original_width": 620,
    "original_height": 826,
    "exif": "{}",
    "sha256": "10cde9d5461c5c6afeb3232564a1d86169cabb795fe71c1ebde8cd599452aa1f"
}