{
    "similarity": 0.30105677247047424,
    "hash": 5437739428458189160,
    "punsafe": 0.00292360782623291,
    "pwatermark": 0.04129159450531006,
    "aesthetic": 7.070035934448242,
    "caption": "Beyonce gives birth to twins",
    "url": "https://www.fairfaxstatic.com.au/content/dam/images/g/u/b/m/a/2/image.related.articleLeadwide.620x349.gwtdnb.png/1497841912893.jpg",
    "key": "000013886",
    "status": "success",
    "error_message": null,
    "width": 620,
    "height": 347,
    "original_width": 620,
    "original_height": 347,
    "exif": "{}",
    "sha256": "02a887c458345619e547f980bf52a81794d25ace7e2b3eeceb971dd13ea2a847"
}