{
    "similarity": 0.2938224971294403,
    "hash": -5245143745793548301,
    "punsafe": 0.00036016106605529785,
    "pwatermark": 0.11257079243659973,
    "aesthetic": 7.0304646492004395,
    "caption": "Used Ford Ranger 2dr Supercab 4.0L XLT 4WD 2003 | Toro Auto. East Windsor, Connecticut",
    "url": "https://invimg2.autofunds.net/InventoryImages/2020/12/04/2399_1728854_22743537_5345304342020.jpg",
    "key": "000014542",
    "status": "success",
    "error_message": null,
    "width": 512,
    "height": 384,
    "original_width": 900,
    "original_height": 675,
    "exif": "{}",
    "sha256": "9b8a9a2d2d74fcb2d01a77315a73fe51e40154650bffd306236520334f984d5a"
}