{
    "similarity": 0.30358847975730896,
    "hash": 8788567083299180508,
    "punsafe": 0.0009493529796600342,
    "pwatermark": 0.3711673319339752,
    "aesthetic": 7.48995304107666,
    "caption": "presentation: African Businessman Character Presentation Demonstration Call Card Greeting Banking Vintage Hand Icon Stylish Background Retro Cartoon Design Vector Illustration",
    "url": "https://us.123rf.com/450wm/ominaesi/ominaesi1608/ominaesi160800088/62191680-african-businessman-character-presentation-demonstration-call-card-greeting-banking-vintage-hand-ico.jpg?ver=6",
    "key": "000013312",
    "status": "success",
    "error_message": null,
    "width": 384,
    "height": 384,
    "original_width": 450,
    "original_height": 450,
    "exif": "{}",
    "sha256": "9047f652c78d0925d37341f6d5b3a5128934c761f70f803a8a3f7b155b0712b6"
}