{
    "similarity": 0.3025759160518646,
    "hash": 5736337260402916502,
    "punsafe": 2.7596626750892028e-05,
    "pwatermark": 0.02825184538960457,
    "aesthetic": 7.9274396896362305,
    "caption": "All butter fruit cake recipe",
    "url": "https://i.pinimg.com/736x/64/06/6a/64066a963de61205e75d715d48afd407--light-fruit-cake-recipe-fruit-cake-recipes.jpg",
    "key": "000014843",
    "status": "success",
    "error_message": null,
    "width": 400,
    "height": 323,
    "original_width": 400,
    "original_height": 323,
    "exif": "{}",
    "sha256": "cd1bd44c17ceb6ffc81aae9a41c1ada9392609e3b2b7e98cd60184095d2b5c2a"
}