{
    "similarity": 0.34857237339019775,
    "hash": 2512756239932049171,
    "punsafe": 0.021155327558517456,
    "pwatermark": 0.04952685162425041,
    "aesthetic": 7.0207061767578125,
    "caption": "20 Red Master Bedroom Design Ideas  Ultimate Home Ideas",
    "url": "https://tse4.mm.bing.net/th?id=OIP.JguhkX0KLAt5IasURVKZ4wHaF6&amp;w=230&amp;h=230&amp;rs=1&amp;pcl=dddddd&amp;o=5&amp;pid=1.1",
    "key": "000013455",
    "status": "success",
    "error_message": null,
    "width": 474,
    "height": 378,
    "original_width": 474,
    "original_height": 378,
    "exif": "{\"Image ExifOffset\": \"26\", \"EXIF Tag 0x4000\": \"32\", \"EXIF Tag 0x4001\": \"0\"}",
    "sha256": "701f71d53ae694bd28a74af634c80fd7d074112cf74ef7c90ab5f1676dece659"
}