{
    "similarity": 0.3290455937385559,
    "hash": -2654933313019310351,
    "punsafe": 0.0031756162643432617,
    "pwatermark": 0.04696986824274063,
    "aesthetic": 7.797973155975342,
    "caption": "Intro to Floral Design Class\u2014July 12th",
    "url": "https://cdn.shopify.com/s/files/1/0251/4041/products/DIRT_class_web_412124aa-b9c4-4332-86f2-99ab37493a2d_600x600.jpg?v=1528157963",
    "key": "000014356",
    "status": "success",
    "error_message": null,
    "width": 600,
    "height": 336,
    "original_width": 600,
    "original_height": 336,
    "exif": "{\"Image Orientation\": \"Horizontal (normal)\", \"Image XResolution\": \"72\", \"Image YResolution\": \"72\", \"Image ResolutionUnit\": \"Pixels/Inch\", \"Image YCbCrPositioning\": \"Centered\", \"Image ExifOffset\": \"102\", \"EXIF ExifVersion\": \"\", \"EXIF ComponentsConfiguration\": \"\", \"EXIF FlashPixVersion\": \"\", \"EXIF ColorSpace\": \"Uncalibrated\", \"EXIF ExifImageWidth\": \"600\", \"EXIF ExifImageLength\": \"336\"}",
    "sha256": "96ea3edbded5ee685d3b5b489c745294f99300665a7415f78d6a7ef548dd2754"
}