{
    "similarity": 0.3316846489906311,
    "hash": -4663163987071768689,
    "punsafe": 0.0012864470481872559,
    "pwatermark": 0.08748813718557358,
    "aesthetic": 7.24748420715332,
    "caption": "Microbes have been found to make strawberries more tasty",
    "url": "https://www.rnz.co.nz/assets/news_crops/48669/eight_col_Microbes_have_been_found_to_make_strawberries_more_tasty_%28Clem_Onojeghuo_via_unsplash.com%29.jpg?1513299158",
    "key": "000014936",
    "status": "success",
    "error_message": null,
    "width": 614,
    "height": 384,
    "original_width": 720,
    "original_height": 450,
    "exif": "{}",
    "sha256": "615bff9a0cb612c4333cc196b1f0b3df9e7672e709e7b161936b0c463f0bf7fa"
}