{
    "similarity": 0.3606512248516083,
    "hash": -3988966253289940714,
    "punsafe": 2.673974904610077e-06,
    "pwatermark": 0.10135437548160553,
    "aesthetic": 7.232951641082764,
    "caption": "Forever Brooch Bouquet",
    "url": "https://img.etsystatic.com/il/f90749/1452190565/il_340x270.1452190565_qsmi.jpg?version=0",
    "key": "000014172",
    "status": "success",
    "error_message": null,
    "width": 340,
    "height": 270,
    "original_width": 340,
    "original_height": 270,
    "exif": "{}",
    "sha256": "2d0b0b5234c93de8183ec04c866fa30aa38e86c4c7ca6b57952409bff0fb01eb"
}